<?xml version="1.0" encoding="utf-8"?>
<!DOCTYPE hibernate-mapping PUBLIC "-//Hibernate/Hibernate Mapping DTD 3.0//EN"
"http://www.hibernate.org/dtd/hibernate-mapping-3.0.dtd">
<!-- 
    Mapping file autogenerated by MyEclipse Persistence Tools
-->
<hibernate-mapping>
    <class name="com.audiovisualcenter.model.Module" table="module" catalog="audiovisualcenter">
        <id name="id" type="java.lang.Integer">
            <column name="id" />
            <generator class="native" />
        </id>
        <property name="name" type="java.lang.String">
            <column name="name" length="20" />
        </property>
        <property name="parentId" type="java.lang.Integer">
            <column name="parent_id" />
        </property>
        <property name="url" type="java.lang.String">
            <column name="url" length="30" />
        </property>
        <property name="status" type="java.lang.Boolean">
            <column name="status" />
        </property>
        <property name="iconClass" type="java.lang.String">
            <column name="icon_class" length="20" />
        </property>
        <property name="seq" type="java.lang.Short">
            <column name="seq" />
        </property>
        <property name="level" type="java.lang.Short">
            <column name="level" />
        </property>
    </class>
</hibernate-mapping>
